jsonapi_client/__init__.py
jsonapi_client/common.py
jsonapi_client/document.py
jsonapi_client/exceptions.py
jsonapi_client/filter.py
jsonapi_client/objects.py
jsonapi_client/relationships.py
jsonapi_client/resourceobject.py
jsonapi_client/session.py
jsonapi_client-0.9.9.dist-info/LICENSE.txt
jsonapi_client-0.9.9.dist-info/METADATA
jsonapi_client-0.9.9.dist-info/WHEEL
jsonapi_client-0.9.9.dist-info/top_level.txt
jsonapi_client-0.9.9.dist-info/RECORD
