Metadata-Version: 2.1
Name: jsonapi-client
Version: 0.9.9
Summary: Comprehensive, yet easy-to-use, pythonic, ORM-like access to JSON API services
Home-page: https://github.com/qvantel/jsonapi-client
Author: Tuomas Airaksinen
Author-email: tuomas.airaksinen@qvantel.com
License: BSD-3
Keywords: JSONAPI JSON API client
Platform: UNKNOWN
Classifier: Programming Language :: Python
Classifier: Programming Language :: Python :: 3.6
Classifier: Topic :: Software Development :: Libraries
Classifier: License :: OSI Approved :: BSD License
Requires-Dist: requests
Requires-Dist: jsonschema
Requires-Dist: aiohttp
